torchquantlib/__init__.py
torchquantlib/calibration/__init__.py
torchquantlib/calibration/model_calibrator.py
torchquantlib/core/__init__.py
torchquantlib/core/asset_pricing/__init__.py
torchquantlib/core/asset_pricing/letsberational.py
torchquantlib/core/asset_pricing/bond/__init__.py
torchquantlib/core/asset_pricing/bond/bond_pricer.py
torchquantlib/core/asset_pricing/bond/fixed_income_forward.py
torchquantlib/core/asset_pricing/money/__init__.py
torchquantlib/core/asset_pricing/money/future_pricer.py
torchquantlib/core/asset_pricing/option/__init__.py
torchquantlib/core/asset_pricing/option/american_option.py
torchquantlib/core/asset_pricing/option/asian_option.py
torchquantlib/core/asset_pricing/option/bermudan_option.py
torchquantlib/core/asset_pricing/option/black_scholes_merton.py
torchquantlib/core/asset_pricing/option/exotics.py
torchquantlib/core/risk/__init__.py
torchquantlib/core/risk/credit_risk/__init__.py
torchquantlib/core/risk/credit_risk/reduced_form_model.py
torchquantlib/core/risk/credit_risk/structural_model.py
torchquantlib/core/risk/greeks/__init__.py
torchquantlib/core/risk/greeks/greeks.py
torchquantlib/core/risk/market_risk/__init__.py
torchquantlib/core/risk/market_risk/expected_shortfall.py
torchquantlib/core/risk/market_risk/scenario_analysis.py
torchquantlib/core/risk/market_risk/stress_testing.py
torchquantlib/core/risk/market_risk/var.py
torchquantlib/core/risk/valuation_adjustment/__init__.py
torchquantlib/core/risk/valuation_adjustment/valuation_adjustment.py
torchquantlib/models/__init__.py
torchquantlib/models/binomial_tree.py
torchquantlib/models/stochastic_model.py
torchquantlib/models/interest_rate/__init__.py
torchquantlib/models/interest_rate/black_karasinski.py
torchquantlib/models/interest_rate/cir.py
torchquantlib/models/interest_rate/hull_white.py
torchquantlib/models/interest_rate/lmm.py
torchquantlib/models/interest_rate/vasicek.py
torchquantlib/models/local_volatility/__init__.py
torchquantlib-1.3.1.dist-info/LICENSE
torchquantlib-1.3.1.dist-info/METADATA
torchquantlib-1.3.1.dist-info/WHEEL
torchquantlib-1.3.1.dist-info/top_level.txt
torchquantlib-1.3.1.dist-info/RECORD
